MANIFEST.in
README.md
setup.py
CanvasJS_Django_Charts.egg-info/PKG-INFO
CanvasJS_Django_Charts.egg-info/SOURCES.txt
CanvasJS_Django_Charts.egg-info/dependency_links.txt
CanvasJS_Django_Charts.egg-info/top_level.txt
django_charts/__init__.py
django_charts/admin.py
django_charts/apps.py
django_charts/models.py
django_charts/tests.py
django_charts/views.py
django_charts/migrations/0001_initial.py
django_charts/migrations/0002_auto_20180707_1500.py
django_charts/migrations/0003_auto_20180707_1501.py
django_charts/migrations/0004_auto_20180707_1505.py
django_charts/migrations/0005_auto_20180707_1612.py
django_charts/migrations/0006_auto_20180707_1631.py
django_charts/migrations/0007_auto_20180708_1729.py
django_charts/migrations/__init__.py
django_charts/templates/django_charts/charts/html/pie.html
django_charts/templates/django_charts/charts/html/spline.html
django_charts/templates/django_charts/charts/js/pie.js.html
django_charts/templates/django_charts/charts/js/spline.js.html
django_charts/templatetags/__init__.py
django_charts/templatetags/djangochart_tags.py