Metadata-Version: 2.1
Name: CanvasJS-Django-Charts
Version: 0.1a0.post1
Summary: App for charts generation for django apps.
Home-page: https://bitbucket.org/elasbit/fc-cloudtrails-sdk-py/src/develop/
Author: Raydel Miranda
Author-email: raydel.miranda.gomez@gmail.com
License: UNKNOWN
Platform: UNKNOWN
Classifier: Programming Language :: Python :: 2
Classifier: Operating System :: OS Independent
